{
  "assets" : {
    "498E23C82CA78A4BCD7BA88E5243B6FC" : {
      "type" : "texture",
      "index" : 0,
      "assetRequest" : {
        "type" : "slide",
        "state" : "contents",
        "slide" : "none"
      },
      "url" : {
        "native" : "assets\/F4C57CAC-C5FE-407D-B0FF-DBA8D673E241.pdf"
      },
      "width" : 1024,
      "height" : 768
    },
    "071F8EFC19C01EC2AD016FE23F6568D2" : {
      "type" : "texture",
      "index" : 3,
      "assetRequest" : {
        "type" : "slide",
        "state" : "contents",
        "slide" : "none"
      },
      "url" : {
        "native" : "assets\/F4C57CAC-C5FE-407D-B0FF-DBA8D673E241.pdf"
      },
      "width" : 1024,
      "height" : 768
    },
    "6CD3670825D0CC306BB68BA34B269CB9" : {
      "type" : "texture",
      "index" : 1,
      "assetRequest" : {
        "type" : "slide",
        "state" : "contents",
        "slide" : "none"
      },
      "url" : {
        "native" : "assets\/F4C57CAC-C5FE-407D-B0FF-DBA8D673E241.pdf"
      },
      "width" : 653,
      "height" : 778
    },
    "AAFBFD3CF5AD24E90D1773B7E5659022" : {
      "type" : "texture",
      "index" : 4,
      "assetRequest" : {
        "type" : "slide",
        "state" : "contents",
        "slide" : "none"
      },
      "url" : {
        "native" : "assets\/F4C57CAC-C5FE-407D-B0FF-DBA8D673E241.pdf"
      },
      "width" : 1024,
      "height" : 768
    },
    "DD97248836D2E19CA9A593B5B325634F" : {
      "type" : "texture",
      "index" : 2,
      "assetRequest" : {
        "type" : "slide",
        "state" : "contents",
        "slide" : "none"
      },
      "url" : {
        "native" : "assets\/F4C57CAC-C5FE-407D-B0FF-DBA8D673E241.pdf"
      },
      "width" : 270,
      "height" : 394
    }
  },
  "events" : [
    {
      "effects" : [
        {
          "beginTime" : 0,
          "baseLayer" : {
            "animations" : [

            ],
            "initialState" : {
              "affineTransform" : [
                1,
                0,
                0,
                1,
                0,
                0
              ],
              "masksToBounds" : false,
              "rotation" : 0,
              "scale" : 1,
              "position" : {
                "pointX" : 512,
                "pointY" : 384
              },
              "width" : 1024,
              "sublayerTransform" : [
                1,
                0,
                0,
                0,
                0,
                1,
                0,
                0,
                0,
                0,
                1,
                0,
                0,
                0,
                0,
                1
              ],
              "contentsRect" : {
                "y" : 0,
                "x" : 0,
                "width" : 1,
                "height" : 1
              },
              "opacity" : 1,
              "edgeAntialiasingMask" : 251658240,
              "height" : 768,
              "hidden" : false,
              "anchorPoint" : {
                "pointX" : 0.5,
                "pointY" : 0.5
              }
            },
            "objectID" : "0",
            "layers" : [
              {
                "animations" : [

                ],
                "initialState" : {
                  "affineTransform" : [
                    1,
                    0,
                    0,
                    1,
                    0,
                    0
                  ],
                  "masksToBounds" : false,
                  "rotation" : 0,
                  "scale" : 1,
                  "position" : {
                    "pointX" : 512,
                    "pointY" : 384
                  },
                  "width" : 1024,
                  "sublayerTransform" : [
                    1,
                    0,
                    0,
                    0,
                    0,
                    1,
                    0,
                    0,
                    0,
                    0,
                    1,
                    -0.00049229876906403734,
                    0,
                    0,
                    0,
                    1
                  ],
                  "contentsRect" : {
                    "y" : 0,
                    "x" : 0,
                    "width" : 1,
                    "height" : 1
                  },
                  "opacity" : 1,
                  "edgeAntialiasingMask" : 251658240,
                  "height" : 768,
                  "hidden" : false,
                  "anchorPoint" : {
                    "pointX" : 0.5,
                    "pointY" : 0.5
                  }
                },
                "layers" : [
                  {
                    "animations" : [

                    ],
                    "layers" : [

                    ],
                    "texturedRectangle" : {
                      "isBackgroundTexture" : false,
                      "singleTextureOpacity" : 1,
                      "textureType" : 0,
                      "textBaseline" : 0,
                      "textXHeight" : 0,
                      "isVerticalText" : false
                    },
                    "initialState" : {
                      "affineTransform" : [
                        1,
                        0,
                        0,
                        1,
                        0,
                        0
                      ],
                      "masksToBounds" : false,
                      "rotation" : 0,
                      "scale" : 1,
                      "position" : {
                        "pointX" : 512,
                        "pointY" : 384
                      },
                      "width" : 1024,
                      "sublayerTransform" : [
                        1,
                        0,
                        0,
                        0,
                        0,
                        1,
                        0,
                        0,
                        0,
                        0,
                        1,
                        0,
                        0,
                        0,
                        0,
                        1
                      ],
                      "contentsRect" : {
                        "y" : 0,
                        "x" : 0,
                        "width" : 1,
                        "height" : 1
                      },
                      "opacity" : 1,
                      "edgeAntialiasingMask" : 0,
                      "height" : 768,
                      "hidden" : false,
                      "anchorPoint" : {
                        "pointX" : 0.5,
                        "pointY" : 0.5
                      }
                    },
                    "texture" : "071F8EFC19C01EC2AD016FE23F6568D2"
                  },
                  {
                    "animations" : [
                      {
                        "timeOffset" : 0,
                        "from" : {
                          "scalar" : false
                        },
                        "beginTime" : 0,
                        "repeatCount" : 0,
                        "fillMode" : "both",
                        "property" : "hidden",
                        "autoreverses" : false,
                        "duration" : 0.01,
                        "to" : {
                          "scalar" : true
                        }
                      }
                    ],
                    "layers" : [

                    ],
                    "texturedRectangle" : {
                      "isBackgroundTexture" : false,
                      "singleTextureOpacity" : 1,
                      "textureType" : 0,
                      "textBaseline" : 0,
                      "textXHeight" : 0,
                      "isVerticalText" : false
                    },
                    "initialState" : {
                      "affineTransform" : [
                        1,
                        0,
                        0,
                        1,
                        0,
                        0
                      ],
                      "masksToBounds" : false,
                      "rotation" : 0,
                      "scale" : 1,
                      "position" : {
                        "pointX" : 512,
                        "pointY" : 384
                      },
                      "width" : 1024,
                      "sublayerTransform" : [
                        1,
                        0,
                        0,
                        0,
                        0,
                        1,
                        0,
                        0,
                        0,
                        0,
                        1,
                        0,
                        0,
                        0,
                        0,
                        1
                      ],
                      "contentsRect" : {
                        "y" : 0,
                        "x" : 0,
                        "width" : 1,
                        "height" : 1
                      },
                      "opacity" : 1,
                      "edgeAntialiasingMask" : 0,
                      "height" : 768,
                      "hidden" : false,
                      "anchorPoint" : {
                        "pointX" : 0.5,
                        "pointY" : 0.5
                      }
                    },
                    "texture" : "AAFBFD3CF5AD24E90D1773B7E5659022"
                  }
                ]
              }
            ]
          },
          "effects" : [

          ],
          "duration" : 0.01,
          "type" : "transition",
          "name" : "none",
          "objectID" : "0"
        }
      ],
      "automaticPlay" : false,
      "hyperlinks" : [

      ],
      "accessibility" : [
        {
          "text" : "12  PROPERTIES",
          "targetRectangle" : {
            "y" : 216.37109375,
            "x" : 743.22418442916864,
            "width" : 202.4459987769128,
            "height" : 106.21681213378906
          }
        },
        {
          "text" : "£27M TURNOVER",
          "targetRectangle" : {
            "y" : 350.37109375,
            "x" : 756.3336843528748,
            "width" : 180.95099948501581,
            "height" : 106.21681213378906
          }
        },
        {
          "text" : "5 ",
          "targetRectangle" : {
            "y" : 484.37109375,
            "x" : 827.21468383789056,
            "width" : 39.476000000000113,
            "height" : 72.25958251953125
          }
        },
        {
          "text" : "YEARS",
          "targetRectangle" : {
            "y" : 558.37109375,
            "x" : 792.36518403577804,
            "width" : 106.56899935626984,
            "height" : 32.216812133789062
          }
        },
        {
          "text" : "OUR financial model is based on a full roll out of our concept within 5 years. We believe our brand will be easy to operationally replicate and we therefore have an aggressive growth strategy to maximise profits and returns for our stakeholders reaching twelve, 80 bedroom leasehold properties by the end of year 5. We will continually monitor our financial performance with weekly, monthly and yearly KPI’s and our forecasting will be scientific rather than emotive. Our KPI’s will be the spine of our success:",
          "targetRectangle" : {
            "y" : 41.85546875,
            "x" : 30.299468994140625,
            "width" : 642.12756347656307,
            "height" : 116.12898254394531
          }
        },
        {
          "text" : "REVENUE - Recorded daily and measured weekly against budget and previous years. Specifically, we will measure ARR, Occupancy, RevPAR and in App purchases",
          "targetRectangle" : {
            "y" : 188.85546875,
            "x" : 30.299468994140625,
            "width" : 642.12756347656318,
            "height" : 32.128982543945312
          }
        },
        {
          "text" : "COST OF SALES - Measured monthly and controlled through strict central purchasing and standardisation within our bedroom stock",
          "targetRectangle" : {
            "y" : 251.85546875,
            "x" : 30.299468994140625,
            "width" : 642.12756347656261,
            "height" : 32.128982543945312
          }
        },
        {
          "text" : "PAYROLL - Budgeted and costed on a weekly basis",
          "targetRectangle" : {
            "y" : 314.85546875,
            "x" : 30.299468994140625,
            "width" : 332.86500000000001,
            "height" : 11.128982543945312
          }
        },
        {
          "text" : "Forecasting will also be a key part of our management tools. We will use business on the books (BOB) reporting to accurately forecast our position against budget and previous years adapting cost controls, bedroom rates and marketing strategies to reflect our financial position.",
          "targetRectangle" : {
            "y" : 356.85546875,
            "x" : 30.299468994140625,
            "width" : 642.12756347656205,
            "height" : 53.128982543945312
          }
        },
        {
          "text" : "THE P&L ",
          "targetRectangle" : {
            "y" : 440.85546875,
            "x" : 30.299468994140625,
            "width" : 60.592999999999989,
            "height" : 11.128982543945312
          }
        },
        {
          "text" : "Our budget is detailed within the appendices of this plan but to further explain some of our forecast",
          "targetRectangle" : {
            "y" : 482.85546875,
            "x" : 30.299468994140625,
            "width" : 640.58800000000019,
            "height" : 11.128982543945312
          }
        },
        {
          "text" : "SALES - During our first year of trading we aim to successfully open one property. We have budgeted for 10 months of trading with an assumption of two months pre-opening training. ",
          "targetRectangle" : {
            "y" : 524.85546875,
            "x" : 30.299468994140625,
            "width" : 642.12756347656307,
            "height" : 32.128982543945312
          }
        },
        {
          "text" : "We believe occupancy will grow quickly and have assumed a challenging but achievable 75% in year 1 supported by an ARR of £104 which is in line with industry standards. As the property reaches maturity we forecast it will produce net sales of £2.8M with a RevPAR of £91 net of VAT.",
          "targetRectangle" : {
            "y" : 587.85546875,
            "x" : 30.299468994140625,
            "width" : 642.12756347656341,
            "height" : 53.128982543945312
          }
        },
        {
          "text" : "After 18 months of trading we will look to open our second property  and steadily build the portfolio, reaching twelve properties and a turnover of £27M by the end of year 5.",
          "targetRectangle" : {
            "y" : 671.85546875,
            "x" : 30.299468994140625,
            "width" : 642.12756347656341,
            "height" : 32.128982543945312
          }
        }
      ],
      "baseLayer" : {
        "animations" : [

        ],
        "initialState" : {
          "affineTransform" : [
            1,
            0,
            0,
            1,
            0,
            0
          ],
          "masksToBounds" : false,
          "rotation" : 0,
          "scale" : 1,
          "position" : {
            "pointX" : 512,
            "pointY" : 384
          },
          "width" : 1024,
          "sublayerTransform" : [
            1,
            0,
            0,
            0,
            0,
            1,
            0,
            0,
            0,
            0,
            1,
            0,
            0,
            0,
            0,
            1
          ],
          "contentsRect" : {
            "y" : 0,
            "x" : 0,
            "width" : 1,
            "height" : 1
          },
          "opacity" : 1,
          "edgeAntialiasingMask" : 251658240,
          "height" : 768,
          "hidden" : false,
          "anchorPoint" : {
            "pointX" : 0.5,
            "pointY" : 0.5
          }
        },
        "objectID" : "0",
        "layers" : [
          {
            "animations" : [

            ],
            "initialState" : {
              "affineTransform" : [
                1,
                0,
                0,
                1,
                0,
                0
              ],
              "masksToBounds" : false,
              "rotation" : 0,
              "scale" : 1,
              "position" : {
                "pointX" : 512,
                "pointY" : 384
              },
              "width" : 1024,
              "sublayerTransform" : [
                1,
                0,
                0,
                0,
                0,
                1,
                0,
                0,
                0,
                0,
                1,
                0,
                0,
                0,
                0,
                1
              ],
              "contentsRect" : {
                "y" : 0,
                "x" : 0,
                "width" : 1,
                "height" : 1
              },
              "opacity" : 1,
              "edgeAntialiasingMask" : 251658240,
              "height" : 768,
              "hidden" : false,
              "anchorPoint" : {
                "pointX" : 0.5,
                "pointY" : 0.5
              }
            },
            "layers" : [
              {
                "animations" : [

                ],
                "initialState" : {
                  "affineTransform" : [
                    1,
                    0,
                    0,
                    1,
                    0,
                    0
                  ],
                  "masksToBounds" : false,
                  "rotation" : 0,
                  "scale" : 1,
                  "position" : {
                    "pointX" : 512,
                    "pointY" : 384
                  },
                  "width" : 1024,
                  "sublayerTransform" : [
                    1,
                    0,
                    0,
                    0,
                    0,
                    1,
                    0,
                    0,
                    0,
                    0,
                    1,
                    0,
                    0,
                    0,
                    0,
                    1
                  ],
                  "contentsRect" : {
                    "y" : 0,
                    "x" : 0,
                    "width" : 1,
                    "height" : 1
                  },
                  "opacity" : 1,
                  "edgeAntialiasingMask" : 251658240,
                  "height" : 768,
                  "hidden" : false,
                  "anchorPoint" : {
                    "pointX" : 0.5,
                    "pointY" : 0.5
                  }
                },
                "layers" : [
                  {
                    "animations" : [

                    ],
                    "layers" : [

                    ],
                    "texturedRectangle" : {
                      "isBackgroundTexture" : true,
                      "singleTextureOpacity" : 1,
                      "textureType" : 1,
                      "textBaseline" : 0,
                      "textXHeight" : 0,
                      "isVerticalText" : false
                    },
                    "initialState" : {
                      "affineTransform" : [
                        1,
                        0,
                        0,
                        1,
                        0,
                        0
                      ],
                      "masksToBounds" : false,
                      "rotation" : 0,
                      "scale" : 1,
                      "position" : {
                        "pointX" : 512,
                        "pointY" : 384
                      },
                      "width" : 1024,
                      "sublayerTransform" : [
                        1,
                        0,
                        0,
                        0,
                        0,
                        1,
                        0,
                        0,
                        0,
                        0,
                        1,
                        0,
                        0,
                        0,
                        0,
                        1
                      ],
                      "contentsRect" : {
                        "y" : 0,
                        "x" : 0,
                        "width" : 1,
                        "height" : 1
                      },
                      "opacity" : 1,
                      "edgeAntialiasingMask" : 0,
                      "height" : 768,
                      "hidden" : false,
                      "anchorPoint" : {
                        "pointX" : 0.5,
                        "pointY" : 0.5
                      }
                    },
                    "texture" : "498E23C82CA78A4BCD7BA88E5243B6FC"
                  }
                ]
              }
            ]
          },
          {
            "animations" : [

            ],
            "initialState" : {
              "affineTransform" : [
                1,
                0,
                0,
                1,
                0,
                0
              ],
              "masksToBounds" : false,
              "rotation" : 0,
              "scale" : 1,
              "position" : {
                "pointX" : 512,
                "pointY" : 384
              },
              "width" : 1024,
              "sublayerTransform" : [
                1,
                0,
                0,
                0,
                0,
                1,
                0,
                0,
                0,
                0,
                1,
                0,
                0,
                0,
                0,
                1
              ],
              "contentsRect" : {
                "y" : 0,
                "x" : 0,
                "width" : 1,
                "height" : 1
              },
              "opacity" : 1,
              "edgeAntialiasingMask" : 251658240,
              "height" : 768,
              "hidden" : false,
              "anchorPoint" : {
                "pointX" : 0.5,
                "pointY" : 0.5
              }
            },
            "layers" : [
              {
                "animations" : [

                ],
                "initialState" : {
                  "affineTransform" : [
                    1,
                    0,
                    0,
                    1,
                    0,
                    0
                  ],
                  "masksToBounds" : false,
                  "rotation" : 0,
                  "scale" : 1,
                  "position" : {
                    "pointX" : 352.79946899414062,
                    "pointY" : 405.85546874999994
                  },
                  "width" : 653,
                  "sublayerTransform" : [
                    1,
                    0,
                    0,
                    0,
                    0,
                    1,
                    0,
                    0,
                    0,
                    0,
                    1,
                    0,
                    0,
                    0,
                    0,
                    1
                  ],
                  "contentsRect" : {
                    "y" : 0,
                    "x" : 0,
                    "width" : 1,
                    "height" : 1
                  },
                  "opacity" : 1,
                  "edgeAntialiasingMask" : 251658240,
                  "height" : 778,
                  "hidden" : false,
                  "anchorPoint" : {
                    "pointX" : 0.5,
                    "pointY" : 0.5
                  }
                },
                "layers" : [
                  {
                    "animations" : [

                    ],
                    "layers" : [

                    ],
                    "texturedRectangle" : {
                      "singleTextureOpacity" : 1,
                      "textXHeight" : 0,
                      "shapePath" : {
                        "lineWidth" : 1,
                        "flatness" : 0.59999999999999998,
                        "lineCapStyle" : 0,
                        "elements" : [
                          {
                            "type" : "MoveToPoint",
                            "points" : [
                              [
                                1.2994689941406286,
                                1.8554687499999467
                              ]
                            ]
                          },
                          {
                            "type" : "AddLine",
                            "points" : [
                              [
                                651.42703247070312,
                                1.8554687499999467
                              ]
                            ]
                          },
                          {
                            "type" : "AddLine",
                            "points" : [
                              [
                                651.42703247070312,
                                776.14453125
                              ]
                            ]
                          },
                          {
                            "type" : "AddLine",
                            "points" : [
                              [
                                1.2994689941406286,
                                776.14453125
                              ]
                            ]
                          },
                          {
                            "type" : "CloseSubpath"
                          },
                          {
                            "type" : "MoveToPoint",
                            "points" : [
                              [
                                1.2994689941406286,
                                1.8554687499999467
                              ]
                            ]
                          }
                        ],
                        "windingRule" : 0,
                        "lineJoinStyle" : 0,
                        "miterLimit" : 10
                      },
                      "isBackgroundTexture" : true,
                      "textBaseline" : 0,
                      "isVerticalText" : false,
                      "textureType" : 5
                    },
                    "initialState" : {
                      "affineTransform" : [
                        1,
                        0,
                        0,
                        1,
                        0,
                        0
                      ],
                      "masksToBounds" : false,
                      "rotation" : 0,
                      "scale" : 1,
                      "position" : {
                        "pointX" : 325.20053100585938,
                        "pointY" : 387.14453125000006
                      },
                      "width" : 653,
                      "sublayerTransform" : [
                        1,
                        0,
                        0,
                        0,
                        0,
                        1,
                        0,
                        0,
                        0,
                        0,
                        1,
                        0,
                        0,
                        0,
                        0,
                        1
                      ],
                      "contentsRect" : {
                        "y" : 0,
                        "x" : 0,
                        "width" : 1,
                        "height" : 1
                      },
                      "opacity" : 1,
                      "edgeAntialiasingMask" : 0,
                      "height" : 778,
                      "hidden" : false,
                      "anchorPoint" : {
                        "pointX" : 0.5,
                        "pointY" : 0.5
                      }
                    },
                    "texture" : "6CD3670825D0CC306BB68BA34B269CB9"
                  }
                ]
              }
            ]
          },
          {
            "animations" : [

            ],
            "initialState" : {
              "affineTransform" : [
                1,
                0,
                0,
                1,
                0,
                0
              ],
              "masksToBounds" : false,
              "rotation" : 0,
              "scale" : 1,
              "position" : {
                "pointX" : 512,
                "pointY" : 384
              },
              "width" : 1024,
              "sublayerTransform" : [
                1,
                0,
                0,
                0,
                0,
                1,
                0,
                0,
                0,
                0,
                1,
                0,
                0,
                0,
                0,
                1
              ],
              "contentsRect" : {
                "y" : 0,
                "x" : 0,
                "width" : 1,
                "height" : 1
              },
              "opacity" : 1,
              "edgeAntialiasingMask" : 251658240,
              "height" : 768,
              "hidden" : false,
              "anchorPoint" : {
                "pointX" : 0.5,
                "pointY" : 0.5
              }
            },
            "layers" : [
              {
                "animations" : [

                ],
                "initialState" : {
                  "affineTransform" : [
                    1,
                    0,
                    0,
                    1,
                    0,
                    0
                  ],
                  "masksToBounds" : false,
                  "rotation" : 0,
                  "scale" : 1,
                  "position" : {
                    "pointX" : 845.23468017578125,
                    "pointY" : 405.37109374999994
                  },
                  "width" : 270,
                  "sublayerTransform" : [
                    1,
                    0,
                    0,
                    0,
                    0,
                    1,
                    0,
                    0,
                    0,
                    0,
                    1,
                    0,
                    0,
                    0,
                    0,
                    1
                  ],
                  "contentsRect" : {
                    "y" : 0,
                    "x" : 0,
                    "width" : 1,
                    "height" : 1
                  },
                  "opacity" : 1,
                  "edgeAntialiasingMask" : 251658240,
                  "height" : 394,
                  "hidden" : false,
                  "anchorPoint" : {
                    "pointX" : 0.5,
                    "pointY" : 0.5
                  }
                },
                "layers" : [
                  {
                    "animations" : [

                    ],
                    "layers" : [

                    ],
                    "texturedRectangle" : {
                      "singleTextureOpacity" : 1,
                      "textXHeight" : 0,
                      "shapePath" : {
                        "lineWidth" : 1,
                        "flatness" : 0.59999999999999998,
                        "lineCapStyle" : 0,
                        "elements" : [
                          {
                            "type" : "MoveToPoint",
                            "points" : [
                              [
                                1.23468017578125,
                                1.3710937499999432
                              ]
                            ]
                          },
                          {
                            "type" : "AddLine",
                            "points" : [
                              [
                                268.5546875,
                                1.3710937499999432
                              ]
                            ]
                          },
                          {
                            "type" : "AddLine",
                            "points" : [
                              [
                                268.5546875,
                                392.62890625
                              ]
                            ]
                          },
                          {
                            "type" : "AddLine",
                            "points" : [
                              [
                                1.23468017578125,
                                392.62890625
                              ]
                            ]
                          },
                          {
                            "type" : "CloseSubpath"
                          },
                          {
                            "type" : "MoveToPoint",
                            "points" : [
                              [
                                1.23468017578125,
                                1.3710937499999432
                              ]
                            ]
                          }
                        ],
                        "windingRule" : 0,
                        "lineJoinStyle" : 0,
                        "miterLimit" : 10
                      },
                      "isBackgroundTexture" : true,
                      "textBaseline" : 0,
                      "isVerticalText" : false,
                      "textureType" : 5
                    },
                    "initialState" : {
                      "affineTransform" : [
                        1,
                        0,
                        0,
                        1,
                        0,
                        0
                      ],
                      "masksToBounds" : false,
                      "rotation" : 0,
                      "scale" : 1,
                      "position" : {
                        "pointX" : 133.76531982421875,
                        "pointY" : 195.62890625000006
                      },
                      "width" : 270,
                      "sublayerTransform" : [
                        1,
                        0,
                        0,
                        0,
                        0,
                        1,
                        0,
                        0,
                        0,
                        0,
                        1,
                        0,
                        0,
                        0,
                        0,
                        1
                      ],
                      "contentsRect" : {
                        "y" : 0,
                        "x" : 0,
                        "width" : 1,
                        "height" : 1
                      },
                      "opacity" : 1,
                      "edgeAntialiasingMask" : 0,
                      "height" : 394,
                      "hidden" : false,
                      "anchorPoint" : {
                        "pointX" : 0.5,
                        "pointY" : 0.5
                      }
                    },
                    "texture" : "DD97248836D2E19CA9A593B5B325634F"
                  }
                ]
              }
            ]
          }
        ]
      }
    }
  ]
}